uwebdavclient/__init__.py
uwebdavclient/client.py
uwebdavclient-0.0.2.data/scripts/uwebdavclient
uwebdavclient-0.0.2.dist-info/LICENSE
uwebdavclient-0.0.2.dist-info/METADATA
uwebdavclient-0.0.2.dist-info/WHEEL
uwebdavclient-0.0.2.dist-info/top_level.txt
uwebdavclient-0.0.2.dist-info/RECORD
