Metadata-Version: 2.1
Name: uwebdavclient
Version: 0.0.2
Summary: Minimal WebDAV client in pure Python
Home-page: https://github.com/ptrktn/uwebdavclient
Author: ptrktn@github
Author-email: {githubuser}@users.noreply.github.com
License: UNKNOWN
Project-URL: Bug Tracker, https://github.com/ptrktn/uwebdavclient/issues
Platform: UNKNOWN
Classifier: Programming Language :: Python :: 3
Classifier: License :: OSI Approved :: GNU General Public License v3 (GPLv3)
Classifier: Operating System :: OS Independent
Requires-Python: >=3.6
License-File: LICENSE
Requires-Dist: requests
